cyberfusion/AptlyApiCli/__init__.py
cyberfusion/AptlyApiCli/package_upload_add.py
python3_cyberfusion_aptly_apicli-1.1.dist-info/METADATA
python3_cyberfusion_aptly_apicli-1.1.dist-info/WHEEL
python3_cyberfusion_aptly_apicli-1.1.dist-info/entry_points.txt
python3_cyberfusion_aptly_apicli-1.1.dist-info/top_level.txt
python3_cyberfusion_aptly_apicli-1.1.dist-info/RECORD
