Metadata-Version: 2.4
Name: python3-cyberfusion-aptly-apicli
Version: 1.1
Summary: API library for Aptly.
Author-email: Cyberfusion <support@cyberfusion.io>
Project-URL: Source, https://github.com/CyberfusionIO/python3-cyberfusion-aptly-apicli
Requires-Dist: certifi==2025.1.31
Requires-Dist: requests==2.32.3
Requires-Dist: python3-cyberfusion-common~=2.12
